{"address":"0x05860d453C7974CbF46508c06CBA14e211c629Ce","coingecko_rank":483,"coingecko_score":29.735,"community_score":33.25,"description":"A Next Generation Blockchain for a Programmable Economy Platform : The Engine Behind the Most Dynamic Enterprise Infrastructure\nEdenChain is a blockchain technology designed specifically with enterprises in mind. It is a fast, secure and reliable third generation blockchain platform that allows all tangible and intangible values to be capitalized through smart contracts, enabling people to freely trade through the internet without intermediaries\n\nThere exist a plethora of tradable asset classes in the world, such as stocks, bonds, real estate and commodities amongst money others. Individuals buy and sell these assets for various financial and non-financial purposes.\n\nAs technology continues to develop, more unique asset classes have begun to emerge, such as copyrights, insurance policies, and derivatives, which all contain tradeable value when certain conditions are met.\n\nWith EdenChain, existing assets can be replaced with blockchain-based tokens and their ownership can be registered; the necessary conditions can be specified through smart contracts according to the characteristics of the asset.","developer_score":0.0,"id":"edenchain","image":{"large":"https://assets.coingecko.com/coins/images/3292/large/y_x5JZcR_400x400.jpg?1547037865","small":"https://assets.coingecko.com/coins/images/3292/small/y_x5JZcR_400x400.jpg?1547037865","thumb":"https://assets.coingecko.com/coins/images/3292/thumb/y_x5JZcR_400x400.jpg?1547037865"},"links":{"bitcointalk_thread_identifier":3101588,"blockchain_site":["https://enjinx.io/eth/token/0x05860d453c7974cbf46508c06cba14e211c629ce","https://etherscan.io/token/0x05860d453c7974cbf46508c06cba14e211c629ce","https://ethplorer.io/address/0x05860d453c7974cbf46508c06cba14e211c629ce"],"facebook_username":"edenchainio","homepage":["http://edenchain.io/"],"subreddit_url":"https://www.reddit.com/r/edenchainio/","telegram_channel_identifier":"edenchainio","twitter_screen_name":"edenchainio"},"liquidity_score":40.299,"market_cap_rank":666,"name":"Edenchain","public_interest_score":24.489,"symbol":"edn","tickers":[{"base":"EDN","market":{"identifier":"idex","name":"Idex"},"target":"ETH"}]}