{"address":"0x280DAACbD812725BAf46E273B84426B1E10aB410","coingecko_rank":4188,"coingecko_score":5.243,"community_score":6.05,"description":"CryptoBexchange is a brand new forward thinking blockchain project that will create one site with three parts;\n\nCryptocurrency exchange\nOnline sports betting\nOnline casino\n\nWe see this as a huge gap in the market that we plan to capitalise on. Currently, there are cryptocurrency exchanges, cryptocurrency betting sites and cryptocurrency casino sites. However, there is no all-in-one trusted site for these activities, and that\u2019s where CryptoBexchange comes in.\n\nCryptoBexchange will have its own cryptocurrency, CBEX. CBEX will be used essentially to power all three elements of the business model. From purchasing and holding CBEX, users will receive discounted trading and withdrawal fees on the exchange, and discounted commission on sports and casino use within the site.","developer_score":0.0,"id":"cryptobexchange","image":{"large":"https://assets.coingecko.com/coins/images/8195/large/cbex.png?1556322577","small":"https://assets.coingecko.com/coins/images/8195/small/cbex.png?1556322577","thumb":"https://assets.coingecko.com/coins/images/8195/thumb/cbex.png?1556322577"},"links":{"blockchain_site":["https://etherscan.io/token/0x280daacbd812725baf46e273b84426b1e10ab410"],"homepage":["https://www.cbex.exchange/"],"telegram_channel_identifier":"cryptobexchange","twitter_screen_name":"cbexexchange"},"liquidity_score":1.0,"market_cap_rank":3534,"name":"CBEX Token","public_interest_score":35.306,"symbol":"cbex","tickers":[{"base":"CBEX","market":{"identifier":"etherflyer","name":"EtherFlyer"},"target":"ETH"},{"base":"CBEX","market":{"identifier":"sistemkoin","name":"Sistemkoin"},"target":"BTC"},{"base":"CBEX","market":{"identifier":"sistemkoin","name":"Sistemkoin"},"target":"DEEX"},{"base":"CBEX","market":{"identifier":"sistemkoin","name":"Sistemkoin"},"target":"ETH"}]}