{"address":"0x297E4e5e59Ad72B1B0A2fd446929e76117be0E0a","coingecko_rank":1812,"coingecko_score":15.104,"community_score":24.501,"description":"SMART VALOR is a platform token of the SMART VALOR exchange which is now a Crypto to Crypto to Fiat. We are working on becoming a fully compliant security token exchange in 2020.","developer_score":0.0,"id":"smart-valor","image":{"large":"https://assets.coingecko.com/coins/images/7231/large/smart_valor.png?1555925772","small":"https://assets.coingecko.com/coins/images/7231/small/smart_valor.png?1555925772","thumb":"https://assets.coingecko.com/coins/images/7231/thumb/smart_valor.png?1555925772"},"links":{"announcement_url":["https://medium.com/smart-valor","https://news.smartvalor.com/news-io-draft/"],"bitcointalk_thread_identifier":5047598,"blockchain_site":["https://enjinx.io/eth/token/0x297e4e5e59ad72b1b0a2fd446929e76117be0e0a","https://etherscan.io/token/0x297e4e5e59ad72b1b0a2fd446929e76117be0e0a","https://ethplorer.io/address/0x297e4e5e59ad72b1b0a2fd446929e76117be0e0a"],"chat_url":["https://open.kakao.com/o/gA4ZV2Y"],"facebook_username":"smartvalorinc","homepage":["https://smartvalor.com/"],"repos_url":{"github":["https://github.com/smartvalor/EIP-Spec"]},"subreddit_url":"https://www.reddit.com/r/SmartValorOfficial/","telegram_channel_identifier":"smartvalor_official","twitter_screen_name":"smartvalorinc"},"liquidity_score":25.118,"market_cap_rank":4130,"name":"Smart Valor","public_interest_score":39.549,"symbol":"valor","tickers":[]}