{"address":"0x34bdf48A8F753de4822a6CFB1FEE275F9b4D662e","coingecko_rank":1628,"coingecko_score":16.725,"community_score":4.436,"description":"The core idea of FACTS is to construct a set of \u201cFactual Content Incentive Mechanism \u201cthat is based on blockchain technology, namely Proof of Facts (PoF). Users can obtain the right of reward allocation through any operational behavior on the factual content. By doing so, they help to solve current problems on the Internet such as massive false content, underpowered creation, low propagation efficiency and so on.FACTS uates content through the \u201cFACTS Index\u201d assessment model which provides a strong credibility reference for content review panel and users. After the assessment, the trusted content is stored in the Facts Pool and then is automatically used to build Facts Graph through the NLP engine.","developer_score":0.0,"id":"facts","image":{"large":"https://assets.coingecko.com/coins/images/8461/large/sFNOkmVx_400x400.jpg?1558690624","small":"https://assets.coingecko.com/coins/images/8461/small/sFNOkmVx_400x400.jpg?1558690624","thumb":"https://assets.coingecko.com/coins/images/8461/thumb/sFNOkmVx_400x400.jpg?1558690624"},"links":{"blockchain_site":["https://etherscan.io/token/0x34bdf48A8F753de4822a6CFB1FEE275F9b4D662e"],"homepage":["http://baike.host/"],"telegram_channel_identifier":"Chinese_Facts","twitter_screen_name":"Facts_IO"},"liquidity_score":1.0,"market_cap_rank":652,"name":"FACTS","public_interest_score":43.892,"symbol":"bkc","tickers":[]}