{"address":"0x34Dd5EDfED51c632d1d4d2502bC901EfB5fdfCD4","coingecko_rank":2886,"coingecko_score":9.292,"community_score":7.304,"description":"Juriseum is a platform for rethinking the way we interact with legal documents & data.\n\nWhile existing systems for legal documents are inefficient, not transparent, and are not secure, our team is building a secure, useful, & easy-to-use platform based on blockchain technology. It will include an immutable and transparent ledger for legal records & documents, and even a digital arbitration system.\n\nAt the end, Our aim is to integrate records and data between involved parties into a unified blockchain ecosystem, which will make existing legal systems truly efficient, transparent, and reliable.","developer_score":0.0,"id":"juriseum","image":{"large":"https://assets.coingecko.com/coins/images/8065/large/iPoG3s1.png?1554110165","small":"https://assets.coingecko.com/coins/images/8065/small/iPoG3s1.png?1554110165","thumb":"https://assets.coingecko.com/coins/images/8065/thumb/iPoG3s1.png?1554110165"},"links":{"announcement_url":["https://medium.com/@briandbwls"],"bitcointalk_thread_identifier":5105615,"blockchain_site":["https://etherscan.io/token/0x34dd5edfed51c632d1d4d2502bc901efb5fdfcd4"],"homepage":["https://juriseum.io"],"repos_url":{"github":["https://github.com/juriseum/tokens"]},"telegram_channel_identifier":"juriseum","twitter_screen_name":"juriseum"},"liquidity_score":1.0,"market_cap_rank":1884,"name":"Juriseum","public_interest_score":24.141,"symbol":"jurm","tickers":[]}