{"address":"0x3E9AFf15644ebFb8a890A9795DA1c0E908c54fDD","coingecko_rank":5242,"coingecko_score":0.2,"community_score":0.0,"description":"The superiority of BDF is using a public chain and applied the smart contract of Ethereum into their system. Thus, it can be reducing the cost and make everything more transparency.\n\nBDFs are used in online shopping, offline shopping malls, entertainment betting, catering payments, real estate hotels, luxury goods, etc. BDFs are committed to building a global payment ecosystem, enhancing the user experience of encrypted currencies in \"all\" consumption scenarios, and establishing a global cashless trading system.\n\nBased on 5G information, BDF tries to build a new global blockchain financial game free trade platform with financial games combined with blockchain as the starting point, and uses blockchain as the bottom to support the whole ecological digitization.","developer_score":0.0,"id":"bdf","image":{"large":"https://assets.coingecko.com/coins/images/9003/large/bdf.PNG?1563576967","small":"https://assets.coingecko.com/coins/images/9003/small/bdf.PNG?1563576967","thumb":"https://assets.coingecko.com/coins/images/9003/thumb/bdf.PNG?1563576967"},"links":{"blockchain_site":["https://etherscan.io/token/0x3e9aff15644ebfb8a890a9795da1c0e908c54fdd"],"homepage":["http://www.bdftoken.online/index.html"]},"liquidity_score":1.0,"market_cap_rank":null,"name":"BDF","public_interest_score":0.0,"symbol":"bdf","tickers":[]}