{"address":"0x45d918e17E30872d7C1CcBaab4a0813Ed0360e46","coingecko_rank":6058,"coingecko_score":1.352,"community_score":5.41,"description":"South Africa's first digital asset pegged 1:1 to the Rand","developer_score":0.0,"id":"digital-rand","image":{"large":"https://assets.coingecko.com/coins/images/9841/large/logo200_%281%29.png?1572577311","small":"https://assets.coingecko.com/coins/images/9841/small/logo200_%281%29.png?1572577311","thumb":"https://assets.coingecko.com/coins/images/9841/thumb/logo200_%281%29.png?1572577311"},"links":{"announcement_url":["https://medium.com/@DigitalRand"],"blockchain_site":["https://etherscan.io/token/0x45d918e17e30872d7c1ccbaab4a0813ed0360e46"],"chat_url":["https://www.linkedin.com/company/digitalrand"],"facebook_username":"Digital-Rand-101861164513259","homepage":["https://digitalrand.co.za/"],"telegram_channel_identifier":"DigitalRandZAR","twitter_screen_name":"DigitalRandZAR"},"liquidity_score":0.0,"market_cap_rank":3569,"name":"Digital Rand","public_interest_score":0.0,"symbol":"dzar","tickers":[]}