{"address":"0x48dEE19C81B89A9aB473361bAE7a19210f2DEaA4","coingecko_rank":6363,"coingecko_score":0.202,"community_score":0.0,"description":"3X Short Shitcoin Index Token (BEARSHIT) is an ERC20 token which seeks a return that corresponds to -3 times the daily return of Shitcoin Index.","developer_score":0.0,"id":"3x-short-shitcoin-index-token","image":{"large":"https://assets.coingecko.com/coins/images/10206/large/683JEXMN_400x400_%281%29.png?1576534838","small":"https://assets.coingecko.com/coins/images/10206/small/683JEXMN_400x400_%281%29.png?1576534838","thumb":"https://assets.coingecko.com/coins/images/10206/thumb/683JEXMN_400x400_%281%29.png?1576534838"},"links":{"blockchain_site":["https://etherscan.io/token/0x48dee19c81b89a9ab473361bae7a19210f2deaa4"],"homepage":["https://ftx.com/tokens/BEARSHIT"]},"liquidity_score":1.0,"market_cap_rank":2755,"name":"3X Short Shitcoin Index Token","public_interest_score":0.025,"symbol":"bearshit","tickers":[{"base":"BEARSHIT","market":{"identifier":"ftx_spot","name":"FTX (Spot)"},"target":"USD"}]}