{"address":"0x49229C3902d49BE6443E01C0251b02780397ab1A","coingecko_rank":2756,"coingecko_score":5.54,"community_score":11.977,"description":"First protocol that provides the infrastructure for direct interoperate in the Heterogeneous Blockchain Ecosystem","developer_score":0.0,"id":"marcopolo","image":{"large":"https://assets.coingecko.com/coins/images/10085/large/MAP_LOGO.png?1597227221","small":"https://assets.coingecko.com/coins/images/10085/small/MAP_LOGO.png?1597227221","thumb":"https://assets.coingecko.com/coins/images/10085/thumb/MAP_LOGO.png?1597227221"},"links":{"announcement_url":["https://blog.naver.com/marcopoloprotocol","https://medium.com/marcopolo-protocol"],"bitcointalk_thread_identifier":5215440,"blockchain_site":["https://etherscan.io/token/0x49229c3902d49be6443e01c0251b02780397ab1a"],"chat_url":["https://discordapp.com/invite/KTJ2Qzc"],"facebook_username":"MarcoPolo-Protocol-107054464162905","homepage":["https://marcopolo.link/"],"repos_url":{"github":["https://github.com/marcopoloprotocol"]},"subreddit_url":"https://www.reddit.com/r/MarcoPoloProtocol/","telegram_channel_identifier":"MarcoPoloMAP","twitter_screen_name":"MarcoPoloGlobal"},"liquidity_score":14.523,"market_cap_rank":null,"name":"MarcoPolo Protocol","public_interest_score":0.001,"symbol":"map","tickers":[]}