{"address":"0x500d15aA5b01E7eb77e4D4C8283Df3E6c49Da754","coingecko_rank":6694,"coingecko_score":1.888,"community_score":7.551,"description":"Hashthereum is one of the most easiest way profitable investment platfrom where you can grow your cryptocurrency.\nWe value trust and aims to give our members a platform of opportunity that leads to success in Blockchain industry.","developer_score":0.0,"id":"hashthereum","image":{"large":"https://assets.coingecko.com/coins/images/10852/large/Pics-Art-04-17-07-02-47.png?1587366957","small":"https://assets.coingecko.com/coins/images/10852/small/Pics-Art-04-17-07-02-47.png?1587366957","thumb":"https://assets.coingecko.com/coins/images/10852/thumb/Pics-Art-04-17-07-02-47.png?1587366957"},"links":{"announcement_url":["https://www.linkedin.com/in/emanuel-ferdinand-5459a6182"],"blockchain_site":["https://etherscan.io/token/0x500d15aA5b01E7eb77e4D4C8283Df3E6c49Da754"],"homepage":["https://hashthereum.info/"],"telegram_channel_identifier":"HashthereumOfficial","twitter_screen_name":"hashthereum"},"liquidity_score":0.0,"market_cap_rank":3612,"name":"Hashthereum","public_interest_score":0.0,"symbol":"heth","tickers":[]}