{"address":"0x556eA1fE7Cb0964e7De8Dfe6CdE63F1E40908541","coingecko_rank":4400,"coingecko_score":1.539,"community_score":6.087,"description":"Registered in Delaware as DigitalUSD LLC, DUSD is a dollar pegged stablecoin and plans to serve a worldwide client base. DUSD will be a regulated stabelcoin with the oversight of U.S. regulators. With superior management style and an advanced product research & development team, DUSD will solve challenges and problems the last generation of stablecoins had encountered.","developer_score":0.0,"id":"digitalusd","image":{"large":"https://assets.coingecko.com/coins/images/10818/large/LOGO_%284%29.png?1584071472","small":"https://assets.coingecko.com/coins/images/10818/small/LOGO_%284%29.png?1584071472","thumb":"https://assets.coingecko.com/coins/images/10818/thumb/LOGO_%284%29.png?1584071472"},"links":{"blockchain_site":["https://etherscan.io/token/0x556eA1fE7Cb0964e7De8Dfe6CdE63F1E40908541"],"facebook_username":"ny.dusd","homepage":["https://www.dusd.com/"],"repos_url":{"github":["https://github.com/Glenguilin/DUSDTOKEN"]},"telegram_channel_identifier":"DUSDG","twitter_screen_name":"DigitalUsd"},"liquidity_score":1.0,"market_cap_rank":null,"name":"DigitalUSD","public_interest_score":0.001,"symbol":"dusd","tickers":[]}