{"address":"0x5abFd418AdB35e89c68313574eB16BdfFc15e607","coingecko_rank":7023,"coingecko_score":1.558,"community_score":5.434,"description":"Timvi is a financial and technological project that has its own ecosystem of services that allow you to store and earn money using the ecosystem\u2019s own stablecoin called Timvi (TMV).","developer_score":0.0,"id":"timvi","image":{"large":"https://assets.coingecko.com/coins/images/10424/large/200.png?1579214290","small":"https://assets.coingecko.com/coins/images/10424/small/200.png?1579214290","thumb":"https://assets.coingecko.com/coins/images/10424/thumb/200.png?1579214290"},"links":{"announcement_url":["https://medium.com/@TimviOfficial"],"bitcointalk_thread_identifier":5185636,"blockchain_site":["https://etherscan.io/token/0x5abfd418adb35e89c68313574eb16bdffc15e607"],"facebook_username":"Timviofficial","homepage":["https://timvi.com/"],"repos_url":{"github":["https://github.com/TimviOfficial/Timvi"]},"twitter_screen_name":"timviofficial"},"liquidity_score":1.0,"market_cap_rank":6680,"name":"Timvi","public_interest_score":0.0,"symbol":"tmv","tickers":[{"base":"TMV","market":{"identifier":"uniswap_v1","name":"Uniswap (v1)"},"target":"ETH"}]}