{"address":"0x6bF0d1AfAF3F9073E3706EE4BEb140b9bf05a3D4","coingecko_rank":4893,"coingecko_score":4.132,"community_score":6.937,"description":"Transburn token is specifically made for dapp game transaction with a coded deflationary 1% per transaction, which means every onchain transaction 1% will be automatically destroyed. This method and application create scarcity for the transburn token to make it surge high base on the law of demand and supply.\n\nThe demand for transburn token will be relatively increase day by day because this is real usecase token that's back up by decrease in total supply upon any transaction made on chain. The more the awareness and interest of blockchain users get involves in usage of transburn the more the velocity of transburn ascending. Transburn is created by blockchain enthusiasts who believe in creating new ideas for the improvement and betterment of block chain industry whereas give the Crypto community to take care of the transburn by promotion and application of marketing strategy. Therefore transburn is largely own by its users and community who believe in new ideas and innovations.","developer_score":0.0,"id":"transburn","image":{"large":"https://assets.coingecko.com/coins/images/9024/large/kigxLSA.png?1563765958","small":"https://assets.coingecko.com/coins/images/9024/small/kigxLSA.png?1563765958","thumb":"https://assets.coingecko.com/coins/images/9024/thumb/kigxLSA.png?1563765958"},"links":{"bitcointalk_thread_identifier":5167479,"blockchain_site":["https://etherscan.io/token/0x6bf0d1afaf3f9073e3706ee4beb140b9bf05a3d4"],"homepage":["https://transburn.com/"],"telegram_channel_identifier":"transburn","twitter_screen_name":"transburn"},"liquidity_score":0.0,"market_cap_rank":3479,"name":"Transburn","public_interest_score":23.977,"symbol":"trb","tickers":[]}