{"address":"0x70861e862E1Ac0C96f853C8231826e469eAd37B1","coingecko_rank":651,"coingecko_score":26.469,"community_score":32.732,"description":"DOS Network - A Decentralized Oracle Service supporting multiple heterogeneous blockchains. DOS Network brings real word data, event and computation power to smart contract in a secure, reliable, efficient and scalable way.","developer_score":0.0,"id":"dos-network","image":{"large":"https://assets.coingecko.com/coins/images/7991/large/DOS.png?1552900889","small":"https://assets.coingecko.com/coins/images/7991/small/DOS.png?1552900889","thumb":"https://assets.coingecko.com/coins/images/7991/thumb/DOS.png?1552900889"},"links":{"announcement_url":["https://medium.com/dos-network"],"bitcointalk_thread_identifier":5103497,"blockchain_site":["https://enjinx.io/eth/token/0x70861e862e1ac0c96f853c8231826e469ead37b1","https://etherscan.io/token/0x70861e862e1ac0c96f853c8231826e469ead37b1","https://ethplorer.io/address/0x70861e862e1ac0c96f853c8231826e469ead37b1"],"homepage":["https://dos.network/"],"repos_url":{"github":["https://github.com/DOSNetwork/core"]},"subreddit_url":"https://www.reddit.com/r/DOSNetwork","telegram_channel_identifier":"dosnetwork_en","twitter_screen_name":"DosNetwork"},"liquidity_score":23.502,"market_cap_rank":970,"name":"DOS Network","public_interest_score":37.554,"symbol":"dos","tickers":[{"base":"DOS","market":{"identifier":"bilaxy","name":"Bilaxy"},"target":"ETH"},{"base":"DOS","market":{"identifier":"coinsuper","name":"Coinsuper"},"target":"ETH"}]}