{"address":"0xbadc39C84dCAA7D25528DC49b467A2c2f10c90Bb","coingecko_rank":5277,"coingecko_score":3.409,"community_score":0.0,"description":"","developer_score":0.0,"id":"vabonchain","image":{"large":"https://assets.coingecko.com/coins/images/9274/large/logo_%2812%29.png?1565689289","small":"https://assets.coingecko.com/coins/images/9274/small/logo_%2812%29.png?1565689289","thumb":"https://assets.coingecko.com/coins/images/9274/thumb/logo_%2812%29.png?1565689289"},"links":{"blockchain_site":["https://etherscan.io/token/0xbadc39c84dcaa7d25528dc49b467a2c2f10c90bb"],"homepage":["https://www.vbcbit.io/"]},"liquidity_score":4.989,"market_cap_rank":2780,"name":"VabonChain","public_interest_score":24.11,"symbol":"vbc","tickers":[]}