{"address":"0xD6e1401a079922469e9b965Cb090ea6fF64C6839","coingecko_rank":1650,"coingecko_score":16.575,"community_score":8.6,"description":"HOLD is a peer-to-peer lending platform that provides instant cash advances against cryptocurrency collateral.","developer_score":0.0,"id":"hold","image":{"large":"https://assets.coingecko.com/coins/images/3830/large/hold_token.jpg?1547038898","small":"https://assets.coingecko.com/coins/images/3830/small/hold_token.jpg?1547038898","thumb":"https://assets.coingecko.com/coins/images/3830/thumb/hold_token.jpg?1547038898"},"links":{"announcement_url":["https://medium.com/@HoldHQ"],"blockchain_site":["https://enjinx.io/eth/token/0xd6e1401a079922469e9b965cb090ea6ff64c6839","https://etherscan.io/token/0xd6e1401a079922469e9b965cb090ea6ff64c6839","https://ethplorer.io/address/0xd6e1401a079922469e9b965cb090ea6ff64c6839"],"homepage":["https://hold.co"],"telegram_channel_identifier":"HoldHQ","twitter_screen_name":"HoldHQ"},"liquidity_score":1.0,"market_cap_rank":779,"name":"Hold","public_interest_score":41.753,"symbol":"hold","tickers":[{"base":"HOLD","market":{"identifier":"bilaxy","name":"Bilaxy"},"target":"ETH"},{"base":"HOLD","market":{"identifier":"idex","name":"Idex"},"target":"ETH"}]}