{"address":"0xD8Bd3958725F216Eb236E9DC65B169DE48101C6A","coingecko_rank":2080,"coingecko_score":13.419,"community_score":8.491,"description":"Globatalent is a global marketplace that tokenizes talent - allowing people all over the world to invest in their favorite competitive athletes, sports idols, and more.\n\nBy tokenizing athletes, teams and clubs, they give everyone the chance to have a stake in your idols, and even bet on future talent. They have made it our goal to bring the best sports idols in the world to this platform.","developer_score":0.0,"id":"globatalent","image":{"large":"https://assets.coingecko.com/coins/images/3161/large/logo-header.8503d5c.png?1548258309","small":"https://assets.coingecko.com/coins/images/3161/small/logo-header.8503d5c.png?1548258309","thumb":"https://assets.coingecko.com/coins/images/3161/thumb/logo-header.8503d5c.png?1548258309"},"links":{"bitcointalk_thread_identifier":2654545,"blockchain_site":["https://enjinx.io/eth/token/0xd8bd3958725f216eb236e9dc65b169de48101c6a","https://etherscan.io/token/0xd8bd3958725f216eb236e9dc65b169de48101c6a","https://ethplorer.io/address/0xd8bd3958725f216eb236e9dc65b169de48101c6a"],"facebook_username":"globatalent.official","homepage":["https://market.globatalent.com/","https://market.globatalent.com/campaigns"],"repos_url":{"github":["https://github.com/Globatalent/marketplace"]},"telegram_channel_identifier":"globatalent","twitter_screen_name":"globatalent"},"liquidity_score":1.0,"market_cap_rank":1195,"name":"Globatalent","public_interest_score":24.582,"symbol":"gbt","tickers":[{"base":"GBT","market":{"identifier":"bitforex","name":"Bitforex"},"target":"BTC"},{"base":"GBT","market":{"identifier":"latoken","name":"LATOKEN"},"target":"BTC"},{"base":"GBT","market":{"identifier":"latoken","name":"LATOKEN"},"target":"ETH"},{"base":"GBT","market":{"identifier":"latoken","name":"LATOKEN"},"target":"USDT"}]}