{"address":"0xD9A12Cde03a86E800496469858De8581D3A5353d","coingecko_rank":2059,"coingecko_score":9.904,"community_score":29.641,"description":"Crowdholding.com is a co-creation platform which connects blockchain businesses with the crypto-community. Businesses can collaborate with the community on Crowdholding to innovate, validate product ideas and get insights from crypto-influencers on topics concerning marketing, sales, IT development and even ICO support.\nOn www.crowdholding.com, blockchain businesses can co-create with the crypto-community by using automated bounties and airdrop feedback tasks. To launch a project on Crowdholding, the businesses purchase YUP token as a mediation. The Crowdholding community earns YUP tokens and other ERC20 tokens for investing time to share and give feedback. Community members can vote for the best submissions and the ranking determines the distribution of the YUP and ERC20 token-rewards. The more votes a submission gets, the more cryptocurrency a user earns. Crowdholding a is rewarding crowdsourcing economy!","developer_score":12.73,"id":"crowdholding","image":{"large":"https://assets.coingecko.com/coins/images/1721/large/crowdholding.png?1547740351","small":"https://assets.coingecko.com/coins/images/1721/small/crowdholding.png?1547740351","thumb":"https://assets.coingecko.com/coins/images/1721/thumb/crowdholding.png?1547740351"},"links":{"bitcointalk_thread_identifier":2082561,"blockchain_site":["https://etherscan.io/token/0xd9a12cde03a86e800496469858de8581d3a5353d","https://ethplorer.io/address/0xd9a12cde03a86e800496469858de8581d3a5353d"],"facebook_username":"Crowdholding","homepage":["https://ico.crowdholding.com/","https://www.crowdholding.com/"],"repos_url":{"github":["https://github.com/crowdholding/yup-token"]},"subreddit_url":"https://www.reddit.com/r/Crowdholding/","telegram_channel_identifier":"Crowdholding","twitter_screen_name":"crowdholding"},"liquidity_score":1.0,"market_cap_rank":null,"name":"Crowdholding","public_interest_score":0.018,"symbol":"yup","tickers":[{"base":"YUP","market":{"identifier":"idex","name":"Idex"},"target":"ETH"}]}