{"address":"0xE477292f1B3268687A29376116B0ED27A9c76170","coingecko_rank":709,"coingecko_score":25.683,"community_score":31.792,"description":"HERO radically changes todays centralized way of online betting. The token enables you to join or create games on the ethereum blockchain. The design of HERO enforces active and passive income streams for all participants in the ecosystem. This transparent and decentralized way of betting breaks the traditional \"the house always wins\" paradigm.","developer_score":21.901,"id":"herocoin","image":{"large":"https://assets.coingecko.com/coins/images/2221/large/herocoin.png?1547744781","small":"https://assets.coingecko.com/coins/images/2221/small/herocoin.png?1547744781","thumb":"https://assets.coingecko.com/coins/images/2221/thumb/herocoin.png?1547744781"},"links":{"bitcointalk_thread_identifier":2116864,"blockchain_site":["https://enjinx.io/eth/token/0xe477292f1b3268687a29376116b0ed27a9c76170","https://etherscan.io/token/0xe477292f1b3268687a29376116b0ed27a9c76170","https://ethplorer.io/address/0xe477292f1b3268687a29376116b0ed27a9c76170"],"facebook_username":"HEROcoinio","homepage":["https://www.herocoin.io/"],"repos_url":{"github":["https://github.com/byteheroes/herocoin"]},"subreddit_url":"https://www.reddit.com/r/HEROcoin","twitter_screen_name":"HEROcoinio"},"liquidity_score":1.0,"market_cap_rank":997,"name":"HEROcoin","public_interest_score":23.985,"symbol":"play","tickers":[]}