{"address":"0xE5F166c0D8872B68790061317BB6CcA04582C912","coingecko_rank":900,"coingecko_score":25.184,"community_score":39.501,"description":"TE-FOOD is a food quality and supply ecosystem for emerging markets, which integrates food supply chain companies, consumers, and authorities into one traceability solution. It starts tracking animals at the farms, collects all logistics and food quality information, and follows them through processing, distribution and sales, right to the consumers. Started in 2016, TE-FOOD serves more than 6000 business customers, and handles 400,000 transactions each day.","developer_score":0.0,"id":"te-food","image":{"large":"https://assets.coingecko.com/coins/images/2325/large/tec.png?1547036538","small":"https://assets.coingecko.com/coins/images/2325/small/tec.png?1547036538","thumb":"https://assets.coingecko.com/coins/images/2325/thumb/tec.png?1547036538"},"links":{"bitcointalk_thread_identifier":2176849,"blockchain_site":["https://enjinx.io/eth/token/0xe5f166c0d8872b68790061317bb6cca04582c912","https://etherscan.io/token/0xe5f166c0d8872b68790061317bb6cca04582c912","https://ethplorer.io/address/0xe5f166c0d8872b68790061317bb6cca04582c912"],"facebook_username":"tefoodintl","homepage":["https://tefoodint.com/"],"subreddit_url":"https://www.reddit.com/r/TE_FOOD/","telegram_channel_identifier":"te_food","twitter_screen_name":"TE_FOOD"},"liquidity_score":3.579,"market_cap_rank":506,"name":"TE-FOOD","public_interest_score":29.288,"symbol":"tfd","tickers":[{"base":"TFD","market":{"identifier":"ddex","name":"DDEX"},"target":"ETH"},{"base":"TFD","market":{"identifier":"ddex","name":"DDEX"},"target":"WETH"},{"base":"TFD","market":{"identifier":"dextop","name":"DEx.top"},"target":"ETH"},{"base":"TFD","market":{"identifier":"forkdelta","name":"ForkDelta"},"target":"ETH"},{"base":"TFD","market":{"identifier":"idex","name":"Idex"},"target":"ETH"},{"base":"TFD","market":{"identifier":"raisex","name":"Raisex"},"target":"BTC"},{"base":"TFD","market":{"identifier":"raisex","name":"Raisex"},"target":"ETH"},{"base":"TFD","market":{"identifier":"saturn_network","name":"Saturn Network"},"target":"ETH"},{"base":"TFD","market":{"identifier":"switcheo","name":"Switcheo"},"target":"ETH"},{"base":"TFD","market":{"identifier":"tokenjar","name":"TokenJar"},"target":"WETH"}]}