{"address":"0xEF1223208d93D7c4934C2D426D939a9a0B917b6E","coingecko_rank":6742,"coingecko_score":2.159,"community_score":7.836,"description":"","developer_score":0.0,"id":"peloton-interactive-inc","image":{"large":"https://assets.coingecko.com/coins/images/11275/large/logo.png?1589866459","small":"https://assets.coingecko.com/coins/images/11275/small/logo.png?1589866459","thumb":"https://assets.coingecko.com/coins/images/11275/thumb/logo.png?1589866459"},"links":{"announcement_url":["https://medium.com/currency-com","https://www.linkedin.com/company/currencycom"],"blockchain_site":["https://etherscan.io/token/0xef1223208d93d7c4934c2d426d939a9a0b917b6e"],"facebook_username":"currencycom","telegram_channel_identifier":"CurrencyComEnglish","twitter_screen_name":"currencycom"},"liquidity_score":1.0,"market_cap_rank":3956,"name":"Peloton Interactive Inc","public_interest_score":0.0,"symbol":"PTON.cx","tickers":[{"base":"PTON","market":{"identifier":"currency","name":"Currency.com"},"target":"USD"}]}