{"address":"0xF45B14ddaBF0F0e275E215b94dD24Ae013a27F12","coingecko_rank":1769,"coingecko_score":15.504,"community_score":27.672,"description":"Synthetic XTZ by Synthetix\n\nTracks the price of Tezos through price feeds supplied by an oracle.","developer_score":0.0,"id":"sxtz","image":{"large":"https://assets.coingecko.com/coins/images/8863/large/sXTZ.png?1562212252","small":"https://assets.coingecko.com/coins/images/8863/small/sXTZ.png?1562212252","thumb":"https://assets.coingecko.com/coins/images/8863/thumb/sXTZ.png?1562212252"},"links":{"blockchain_site":["https://etherscan.io/token/0xF45B14ddaBF0F0e275E215b94dD24Ae013a27F12"],"chat_url":["https://discordapp.com/invite/AEdUHzt"],"homepage":["https://www.synthetix.io/"],"subreddit_url":"https://www.reddit.com/r/synthetix_io","twitter_screen_name":"synthetix_io"},"liquidity_score":30.759,"market_cap_rank":3218,"name":"sXTZ","public_interest_score":24.346,"symbol":"sxtz","tickers":[{"base":"SXTZ","market":{"identifier":"synthetix","name":"Synthetix Exchange"},"target":"IBTC"},{"base":"SXTZ","market":{"identifier":"synthetix","name":"Synthetix Exchange"},"target":"IETH"},{"base":"SXTZ","market":{"identifier":"synthetix","name":"Synthetix Exchange"},"target":"ILINK"},{"base":"SXTZ","market":{"identifier":"synthetix","name":"Synthetix Exchange"},"target":"ILTC"},{"base":"SXTZ","market":{"identifier":"synthetix","name":"Synthetix Exchange"},"target":"IMKR"},{"base":"SXTZ","market":{"identifier":"synthetix","name":"Synthetix Exchange"},"target":"ITRX"},{"base":"SXTZ","market":{"identifier":"synthetix","name":"Synthetix Exchange"},"target":"IXRP"},{"base":"SXTZ","market":{"identifier":"synthetix","name":"Synthetix Exchange"},"target":"IXTZ"},{"base":"SXTZ","market":{"identifier":"synthetix","name":"Synthetix Exchange"},"target":"SBTC"},{"base":"SXTZ","market":{"identifier":"synthetix","name":"Synthetix Exchange"},"target":"SETH"},{"base":"SXTZ","market":{"identifier":"synthetix","name":"Synthetix Exchange"},"target":"SLTC"},{"base":"SXTZ","market":{"identifier":"synthetix","name":"Synthetix Exchange"},"target":"SXRP"},{"base":"STRX","market":{"identifier":"synthetix","name":"Synthetix Exchange"},"target":"SXTZ"},{"base":"SBNB","market":{"identifier":"synthetix","name":"Synthetix Exchange"},"target":"SXTZ"}]}