{"address":"0xf5839F46Ed000d70cbab1FCD03E29E85F3aecD82","coingecko_rank":5483,"coingecko_score":2.687,"community_score":0.0,"description":"BitCardTour is a global financial asset payment platform jointly launched by the world's second largest credit card international organization, MasterCard International and Singapore's Bitcard Tour financial institutions.\n\nBitCardTour uses the blockchain technology and the MasterCard payment system to create a global financial payment system for cross-border, trade, consumption, payment, seamless exchange of currency, wealth management, finance and other integrated digital currency.","developer_score":0.0,"id":"bitcardtour","image":{"large":"https://assets.coingecko.com/coins/images/8900/large/bct.PNG?1562655361","small":"https://assets.coingecko.com/coins/images/8900/small/bct.PNG?1562655361","thumb":"https://assets.coingecko.com/coins/images/8900/thumb/bct.PNG?1562655361"},"links":{"blockchain_site":["https://etherscan.io/token/0xf5839f46ed000d70cbab1fcd03e29e85f3aecd82"],"homepage":["http://www.bitcardtour.com/"]},"liquidity_score":1.0,"market_cap_rank":4169,"name":"BitCardTour","public_interest_score":24.873,"symbol":"bct","tickers":[]}