{"address":"0xF6dBE88bA55f1793Ff0773c9B1275300f830914F","description":"Asian Dragon is a \u201cCoin of Wealth\u201d the future transaction of the people using the existing Blockchain platform and powering it as the new Currency tokens for the Asian people.","id":"asian-dragon","links":{"bitcointalk_thread_identifier":5107135,"blockchain_site":["https://etherscan.io/token/0xf6dbe88ba55f1793ff0773c9b1275300f830914f"],"chat_url":["https://asiandragontechnology.slack.com","https://discord.gg/gQrammu"],"facebook_username":"asiandragontech","homepage":["https://www.asiandragoncoin.com"],"repos_url":{"github":["https://github.com/asiandragoncoin/COntractABI"]},"telegram_channel_identifier":"adgncoin","twitter_screen_name":"CoinAsian"},"name":"Asian Dragon","symbol":"ad","tickers":[{"base":"AD","market":{"identifier":"saturn_network","name":"Saturn Network"},"target":"ETH"}]}