{"address":"0xf6Fd82dEdBBe0ffadb5e1ecc2a283AB52B9ED2B0","coingecko_rank":2167,"coingecko_score":12.729,"community_score":20.308,"description":"We are pursuing the opportunity to become the \u201cBooking.com, Steemit and Salesforce of Healthcare\u201d, with a model capable of generating $100B+ of potential revenue.\n\nWe intensely focus on UX and hiding the complexity of crypto world, creating a gateway for a vast amount of users and money to join the biggest revolution since widespread internet adoption.\n\nWe have already tested our strategy, 2,500,000 people use our site yearly (Doklist.com), and we currently potentially reach 230M people on 2 opposing sides of the world (Brazil and Hungary).\n\nTaking advantage of the blockchain-based incentive system and the resulting high-quality global database, we aim to quickly become a dominant player in rapidly growing markets (medical tourism and pharmaceutical communication research and advertisement), currently worth more than $117 billion globally.","developer_score":19.073,"id":"etheal","image":{"large":"https://assets.coingecko.com/coins/images/3267/large/heal.png?1547037807","small":"https://assets.coingecko.com/coins/images/3267/small/heal.png?1547037807","thumb":"https://assets.coingecko.com/coins/images/3267/thumb/heal.png?1547037807"},"links":{"bitcointalk_thread_identifier":2240173,"blockchain_site":["https://etherscan.io/token/0xf6fd82dedbbe0ffadb5e1ecc2a283ab52b9ed2b0","https://ethplorer.io/address/0xf6fd82dedbbe0ffadb5e1ecc2a283ab52b9ed2b0"],"facebook_username":"etheal.platform","homepage":["https://etheal.com/"],"repos_url":{"github":["https://github.com/thesved/etheal-sale"]},"subreddit_url":"https://www.reddit.com/r/Etheal","twitter_screen_name":"etheal_com"},"liquidity_score":1.0,"market_cap_rank":4988,"name":"Etheal","public_interest_score":26.835,"symbol":"heal","tickers":[{"base":"HEAL","market":{"identifier":"yobit","name":"YoBit"},"target":"RUR"},{"base":"HEAL","market":{"identifier":"yobit","name":"YoBit"},"target":"WAVES"}]}