{"address":"0xFbcFD010d007d10D49f516bB738F4aED12880225","coingecko_rank":5458,"coingecko_score":3.387,"community_score":0.0,"description":"Wildlife is charity project to campaigning protecting wildlife","developer_score":0.0,"id":"wild","image":{"large":"https://assets.coingecko.com/coins/images/8973/large/200200.png?1563525596","small":"https://assets.coingecko.com/coins/images/8973/small/200200.png?1563525596","thumb":"https://assets.coingecko.com/coins/images/8973/thumb/200200.png?1563525596"},"links":{"bitcointalk_thread_identifier":5160782,"blockchain_site":["https://etherscan.io/token/0xfbcfd010d007d10d49f516bb738f4aed12880225"],"chat_url":["https://discord.gg/Sm9QvyN"],"facebook_username":"wildlifetoken","homepage":["https://wildlifetoken.org/"],"repos_url":{"github":["https://github.com/Rubby21/WildLife"]},"telegram_channel_identifier":"WildLife_Token","twitter_screen_name":"wildlifetoken"},"liquidity_score":0.0,"market_cap_rank":2204,"name":"WildLife","public_interest_score":33.868,"symbol":"wild","tickers":[]}