{"address":"0xfdFE8b7aB6CF1bD1E3d14538Ef40686296C42052","coingecko_rank":3134,"coingecko_score":8.126,"community_score":21.972,"description":"Skraps is a micro-investing platform where users can invest by rounding off their fiat transactions & investing that spare change in cryptocurrencies. SKRP token will be used to pay transaction fees.","developer_score":0.0,"id":"skraps","image":{"large":"https://assets.coingecko.com/coins/images/7987/large/60EnDfxK_400x400.jpg?1552888803","small":"https://assets.coingecko.com/coins/images/7987/small/60EnDfxK_400x400.jpg?1552888803","thumb":"https://assets.coingecko.com/coins/images/7987/thumb/60EnDfxK_400x400.jpg?1552888803"},"links":{"bitcointalk_thread_identifier":2520387,"blockchain_site":["https://etherscan.io/token/0xfdfe8b7ab6cf1bd1e3d14538ef40686296c42052"],"facebook_username":"SKRAPSAPP","homepage":["https://skraps.io"],"repos_url":{"github":["https://github.com/SkrapsIO/ico"]},"subreddit_url":"https://www.reddit.com/r/SKRAPSio/","telegram_channel_identifier":"SkrapsOfficial","twitter_screen_name":"SkrapsApp"},"liquidity_score":1.0,"market_cap_rank":3432,"name":"Skraps","public_interest_score":24.327,"symbol":"skrp","tickers":[{"base":"SKRP","market":{"identifier":"yobit","name":"YoBit"},"target":"DOGE"},{"base":"SKRP","market":{"identifier":"yobit","name":"YoBit"},"target":"RUR"}]}