{"address":"0xFF603F43946A3A28DF5E6A73172555D8C8b02386","coingecko_rank":695,"coingecko_score":26.011,"community_score":7.821,"description":"Concept and applications based on the blockchain technology are disrupting and transforming the traditional economy and will eventually form a new comprehensive and efficient system. ONEROOT aims to make use of the immutability, transparency and traceability of blockchain while embracing values of decentralization and shared economy to build a network of value that better fits with the characteristics of distributed network and tokenization of assets. Upholding the ideals of sharing and co-operation, our team provides infrastructures for digital assets and co-builds an ecosystem in conformity with characteristics of decentralization, fastening this migration of value.","developer_score":0.0,"id":"oneroot-network","image":{"large":"https://assets.coingecko.com/coins/images/2520/large/OneRootNetwork.PNG?1558014608","small":"https://assets.coingecko.com/coins/images/2520/small/OneRootNetwork.PNG?1558014608","thumb":"https://assets.coingecko.com/coins/images/2520/thumb/OneRootNetwork.PNG?1558014608"},"links":{"blockchain_site":["https://enjinx.io/eth/token/0xff603f43946a3a28df5e6a73172555d8c8b02386","https://etherscan.io/token/0xff603f43946a3a28df5e6a73172555d8c8b02386","https://ethplorer.io/address/0xff603f43946a3a28df5e6a73172555d8c8b02386"],"homepage":["https://www.oneroot.io/en"],"telegram_channel_identifier":"OneRootProject","twitter_screen_name":"OneRootNetwork"},"liquidity_score":48.737,"market_cap_rank":422,"name":"OneRoot Network","public_interest_score":26.103,"symbol":"rnt","tickers":[{"base":"RNT","market":{"identifier":"bitsdaq","name":"Bitsdaq"},"target":"USDT"},{"base":"RNT","market":{"identifier":"lbank","name":"LBank"},"target":"USDT"}]}